bianyi.py
bianyi_package-0.1.dist-info/METADATA
bianyi_package-0.1.dist-info/WHEEL
bianyi_package-0.1.dist-info/top_level.txt
bianyi_package-0.1.dist-info/RECORD
